lexographer/__init__.py
lexographer/version.txt
lexographer/enumerations/__init__.py
lexographer/exceptions/__init__.py
lexographer/lexer/__init__.py
lexographer/logging/__init__.py
lexographer/parser/__init__.py
lexographer/tokenizer/__init__.py
lexographer/tokenizer/token/__init__.py
lexographer/tokenizer/tokens/__init__.py
lexographer-0.8.1.dist-info/METADATA
lexographer-0.8.1.dist-info/WHEEL
lexographer-0.8.1.dist-info/top_level.txt
lexographer-0.8.1.dist-info/zip-safe
lexographer-0.8.1.dist-info/RECORD
