Metadata-Version: 2.4
Name: lexographer
Version: 0.8.1
Summary: A Pure Python Lexer & Tokenizer Base Library
Author: Daniel Sissman
License-Expression: MIT
Project-URL: documentation, https://github.com/bluebinary/lexographer/blob/main/README.md
Project-URL: changelog, https://github.com/bluebinary/lexographer/blob/main/CHANGELOG.md
Project-URL: repository, https://github.com/bluebinary/lexographer
Project-URL: issues, https://github.com/bluebinary/lexographer/issues
Project-URL: homepage, https://github.com/bluebinary/lexographer
Keywords: lexing,lexer,tokenizer,tokeniser,parser
Platform: any
Classifier: Programming Language :: Python :: 3
Classifier: Programming Language :: Python :: 3.10
Classifier: Programming Language :: Python :: 3.11
Classifier: Programming Language :: Python :: 3.12
Classifier: Programming Language :: Python :: 3.13
Requires-Python: >=3.10
Requires-Dist: enumerific>=1.0.9
Provides-Extra: development
Requires-Dist: black==26.1.0; extra == "development"
Requires-Dist: pytest==8.3.*; extra == "development"
Requires-Dist: pytest-codeblocks==0.17.0; extra == "development"
Requires-Dist: pyflakes; extra == "development"
Provides-Extra: distribution
Requires-Dist: build; extra == "distribution"
Requires-Dist: twine; extra == "distribution"
Requires-Dist: wheel; extra == "distribution"
